{"blocks":{"languageVersion":0,"blocks":[{"type":"niryo_one_update_tool","id":"b1H0r;*ZD`8US*q!^MW_","x":-345,"y":-635,"next":{"block":{"type":"niryo_ned2_open_gripper","id":"w8m6m?BCH|JaATMYa50A","fields":{"OPEN_TORQUE":100,"OPEN_HOLD_TORQUE":100},"next":{"block":{"type":"niryo_one_move_pose_from_pose","id":"J]R{rAD2-2@b/X9GL[h0","fields":{"MOVE_POSE_METHOD_SELECT":"MoveCommandType.POSE"},"inputs":{"POSE":{"block":{"type":"niryo_one_pose","id":"{1/tqQcy,4SD-;.f)+5`","data":"rad","inputs":{"x":{"block":{"type":"math_number","id":"Ty[;NgYzsB!{#C/?)6{v","fields":{"NUM":0.14}}},"y":{"block":{"type":"math_number","id":"=m|OWioh(b~;l`hn.M#+","fields":{"NUM":0}}},"z":{"block":{"type":"math_number","id":"r(-p=~W:*aXZ404W/.$}","fields":{"NUM":0.203}}},"roll":{"block":{"type":"math_number","id":"Y5GgoZTxrR!clnBDoW1W","fields":{"NUM":-0.006}}},"pitch":{"block":{"type":"math_number","id":"8Iue0}~z9ws`(IB*-Dga","fields":{"NUM":0.75}}},"yaw":{"block":{"type":"math_number","id":"OUOiTuy;TBX_$V%|~T]j","fields":{"NUM":-0.001}}}}}}},"next":{"block":{"type":"niryo_one_move_pose_from_pose","id":"Yze7jHlB0~Q{|6tw=@do","fields":{"MOVE_POSE_METHOD_SELECT":"MoveCommandType.POSE"},"inputs":{"POSE":{"block":{"type":"niryo_one_pose","id":"J`6!HaMVmS*z]uYaRmc?","data":"rad","inputs":{"x":{"block":{"type":"math_number","id":"jh+mmZaL`s]}}YOg9s|!","fields":{"NUM":0.143}}},"y":{"block":{"type":"math_number","id":"feI~J6ZnK?C6#f?P{ayH","fields":{"NUM":-0.182}}},"z":{"block":{"type":"math_number","id":")70k_!8,VVIf8IrfI[$4","fields":{"NUM":0.12}}},"roll":{"block":{"type":"math_number","id":"tV6~z.8C%%lp*ZqzjL{M","fields":{"NUM":3.064}}},"pitch":{"block":{"type":"math_number","id":"``WuQEk19`+$}[tzx.Bw","fields":{"NUM":1.524}}},"yaw":{"block":{"type":"math_number","id":"oVK95Yf03u/Legd^G]-b","fields":{"NUM":3.139}}}}}}},"next":{"block":{"type":"niryo_one_move_pose_from_pose","id":".VZR-m_+]+B`%-,!m.j%","fields":{"MOVE_POSE_METHOD_SELECT":"MoveCommandType.POSE"},"inputs":{"POSE":{"block":{"type":"niryo_one_pose","id":"}QD4ro;1V`x714*ATM1K","data":"rad","inputs":{"x":{"block":{"type":"math_number","id":"fTM[6NYC`_t,;|^t7:42","fields":{"NUM":0.143}}},"y":{"block":{"type":"math_number","id":".hLEn3A{h1S6]Ws[k@!^","fields":{"NUM":-0.182}}},"z":{"block":{"type":"math_number","id":"xnUq#n#6dIm2;G7NS%K-","fields":{"NUM":0.088}}},"roll":{"block":{"type":"math_number","id":"Zt*EFIDq!n6j;1*[twAf","fields":{"NUM":2.755}}},"pitch":{"block":{"type":"math_number","id":"t{E3/xO_gpwx`|C6Df8~","fields":{"NUM":1.514}}},"yaw":{"block":{"type":"math_number","id":"Su~|VjLSE`v0TSdxR}w%","fields":{"NUM":2.832}}}}}}},"next":{"block":{"type":"niryo_ned2_close_gripper","id":"Wvi8@F_SB/pgJ5wxhrOe","fields":{"CLOSE_TORQUE":100,"CLOSE_HOLD_TORQUE":100},"next":{"block":{"type":"niryo_one_move_pose_from_pose","id":"-oWr/?.k4@IsupfzSBrh","fields":{"MOVE_POSE_METHOD_SELECT":"MoveCommandType.POSE"},"inputs":{"POSE":{"block":{"type":"niryo_one_pose","id":"e8I{sKxvp[bK16V=}1=P","data":"rad","inputs":{"x":{"block":{"type":"math_number","id":"S1+PSv-~I|,c)`nx,8k6","fields":{"NUM":0.171}}},"y":{"block":{"type":"math_number","id":"+8dO5=b4cu0=l1:2|Gu.","fields":{"NUM":-0.011}}},"z":{"block":{"type":"math_number","id":"G7Lo-P]JUHd-]/4YZ%X(","fields":{"NUM":0.13}}},"roll":{"block":{"type":"math_number","id":"T)!i!5+zwm*`n20_1bVp","fields":{"NUM":-2.802}}},"pitch":{"block":{"type":"math_number","id":"NGy8;Vi6sH)C8?x?eN(o","fields":{"NUM":1.508}}},"yaw":{"block":{"type":"math_number","id":"$+wDI$PRaU|POVE#Y9hY","fields":{"NUM":-2.752}}}}}}},"next":{"block":{"type":"niryo_one_move_pose_from_pose","id":"WpT%B*Bw$hT#j35Z+;=W","fields":{"MOVE_POSE_METHOD_SELECT":"MoveCommandType.POSE"},"inputs":{"POSE":{"block":{"type":"niryo_one_pose","id":"dXve7jL^[wPvrw9!W)R+","data":"rad","inputs":{"x":{"block":{"type":"math_number","id":"m9/,+^It?WwoibIjJrq/","fields":{"NUM":0.171}}},"y":{"block":{"type":"math_number","id":"U6V0#k1pet:]Z80Bm`mI","fields":{"NUM":-0.01}}},"z":{"block":{"type":"math_number","id":"KlLH6x^`Ui`Vv8bNmu4M","fields":{"NUM":0.086}}},"roll":{"block":{"type":"math_number","id":"TJSesXUMLrf]?Cg]L|mn","fields":{"NUM":-2.771}}},"pitch":{"block":{"type":"math_number","id":"YkdpAQf04x9GP2.4ilJ|","fields":{"NUM":1.552}}},"yaw":{"block":{"type":"math_number","id":"l|--)iylw!ikV,OgNB_/","fields":{"NUM":-2.726}}}}}}},"next":{"block":{"type":"niryo_ned2_open_gripper","id":"Kq[@X~3,=+TwlMge,`*:","fields":{"OPEN_TORQUE":100,"OPEN_HOLD_TORQUE":100}}}}}}}}}}}}}}}}}}]}}
